__init__.py
sankey.py
tests/__init__.py
tests/generic_test.py
tests/test_fruit_defaults.py
tests/test_fruit_setup.py
auSankey-2024.0.dist-info/LICENSE
auSankey-2024.0.dist-info/METADATA
auSankey-2024.0.dist-info/WHEEL
auSankey-2024.0.dist-info/top_level.txt
auSankey-2024.0.dist-info/RECORD
