Metadata-Version: 2.1
Name: auSankey
Version: 2024.0
Summary: Left-right Sankey diagrams
Author-email: Will Robertson <wspr81@gmail.com>
Maintainer-email: Will Robertson <wspr81@gmail.com>
License: GNU GENERAL PUBLIC LICENSE
Project-URL: Homepage, https://github.com/AUMAG/auSankey
Project-URL: Documentation, https://aumag.github.io/auSankey/
Project-URL: Repository, https://github.com/AUMAG/auSankey.git
Project-URL: Issues, https://github.com/AUMAG/auSankey/issues
Classifier: Development Status :: 4 - Beta
Classifier: License :: OSI Approved :: GNU General Public License v3 (GPLv3)
Classifier: Programming Language :: Python :: 3.9
Classifier: Programming Language :: Python :: 3.10
Classifier: Programming Language :: Python :: 3.11
Requires-Python: >=3.9
License-File: LICENSE
Requires-Dist: matplotlib
Requires-Dist: numpy
Requires-Dist: pandas
Provides-Extra: dev
Requires-Dist: pylint ; extra == 'dev'
Requires-Dist: pytest ; extra == 'dev'
Requires-Dist: flake8 ; extra == 'dev'
Requires-Dist: coverage ; extra == 'dev'
Requires-Dist: coveralls ; extra == 'dev'
